streamlit_notify/__init__.py
streamlit_notify/functional.py
streamlit_notify/notification_dataclass.py
streamlit_notify/notification_queue.py
streamlit_notify/status_element_types.py
streamlit_notify/status_elements.py
streamlit_notify/utils.py
streamlit_notify-0.3.0.dist-info/METADATA
streamlit_notify-0.3.0.dist-info/WHEEL
streamlit_notify-0.3.0.dist-info/top_level.txt
streamlit_notify-0.3.0.dist-info/RECORD
