Metadata-Version: 2.4
Name: streamlit-notify
Version: 0.3.0
Summary: A Streamlit component that provides toast notifications that persist across reruns
Author-email: Patrick Garrett <pgarrett@scripps.edu>
Classifier: Programming Language :: Python :: 3
Classifier: License :: OSI Approved :: MIT License
Classifier: Operating System :: OS Independent
Requires-Python: >=3.7
Requires-Dist: streamlit
Requires-Dist: packaging
